MANIFEST.in
ez_setup.py
setup.py
django_yui_loader.egg-info/PKG-INFO
django_yui_loader.egg-info/SOURCES.txt
django_yui_loader.egg-info/dependency_links.txt
django_yui_loader.egg-info/top_level.txt
yui_loader/__init__.py
yui_loader/components.py
yui_loader/context_processors.py
yui_loader/loader.py
yui_loader/middleware.py
yui_loader/models.py
yui_loader/module_info_2_5_1.py
yui_loader/module_info_2_7_0.py