Metadata-Version: 1.1
Name: django-yui-loader
Version: 0.3.2
Summary: Server-side middleware which implements some of the functionality in the Yahoo User Interface Loader component.
Home-page: http://github.com/akaihola/django-yui-loader
Author: Antti Kaihola
Author-email: akaihol+django@ambitone.com
License: UNKNOWN
Platform: UNKNOWN
Classifier: License :: OSI Approved :: BSD License
Classifier: Programming Language :: Python
Classifier: Environment :: Web Environment
Classifier: Intended Audience :: Developers
Classifier: Operating System :: OS Independent
Classifier: Topic :: Internet :: WWW/HTTP
Classifier: Topic :: Utilities
